reactpy_forms/__init__.py
reactpy_forms/field_model.py
reactpy_forms/form_model.py
reactpy_forms/forms_core.py
reactpy_forms/types.py
reactpy_forms-0.0.8.dist-info/LICENSE
reactpy_forms-0.0.8.dist-info/METADATA
reactpy_forms-0.0.8.dist-info/WHEEL
reactpy_forms-0.0.8.dist-info/RECORD
